{
  "users": [
    {
      "name": "admin",
      "password": "password",
      "tags": "administrator"
    },
    {
      "name": "consumer",
      "password": "empty",
      "tags": ""
    }
  ],
  "vhosts": [
    {
      "name": "/"
    }
  ],
  "permissions": [
    {
      "user": "admin",
      "vhost": "/",
      "configure": ".*",
      "write": ".*",
      "read": ".*"
    },
    {
      "user": "consumer",
      "vhost": "/",
      "configure": "",
      "write": ".*",
      "read": ".*"
    }
  ],
  "exchanges": [
    {
      "name": "spring-boot-exchange",
      "vhost": "/",
      "type": "direct",
      "durable": true,
      "auto_delete": false,
      "internal": false,
      "arguments": {}
    }
  ],
  "queues": [
    {
      "name": "AccountActivated",
      "vhost": "/",
      "durable": true,
      "auto_delete": false,
      "arguments": {
        "x-message-ttl": 3600000
      }
    },
    {
      "name": "CommandQueue",
      "vhost": "/",
      "durable": true,
      "auto_delete": false,
      "arguments": {
        "x-message-ttl": 3600000
      }
    }
  ],
  "bindings": [
    {
      "source": "spring-boot-exchange",
      "vhost": "/",
      "destination": "AccountActivated",
      "destination_type": "queue",
      "routing_key": "AccountActivatedEvent",
      "arguments": {}
    }
  ]
}